wwpdb/utils/oe_util/__init__.py
wwpdb/utils/oe_util/build/OeBuildModelMol.py
wwpdb/utils/oe_util/build/OeBuildMol.py
wwpdb/utils/oe_util/build/OeChemCompIoUtils.py
wwpdb/utils/oe_util/build/OeDescriptorUtils.py
wwpdb/utils/oe_util/build/OePersist.py
wwpdb/utils/oe_util/build/PdbxBuildChemComp.py
wwpdb/utils/oe_util/build/__init__.py
wwpdb/utils/oe_util/oedepict/OeAlignDepict.py
wwpdb/utils/oe_util/oedepict/OeAlignDepictUtils.py
wwpdb/utils/oe_util/oedepict/OeDepict.py
wwpdb/utils/oe_util/oedepict/__init__.py
wwpdb/utils/oe_util/oedepict/modMCSAlign.py
wwpdb/utils/oe_util/oedepict/simple-example.py
wwpdb_utils_oe_util-0.9.0.dist-info/METADATA
wwpdb_utils_oe_util-0.9.0.dist-info/WHEEL
wwpdb_utils_oe_util-0.9.0.dist-info/RECORD
